{
  "harness": "capture_v8.py",
  "generated_at": "2026-06-23T19:16:15.207105",
  "git": {
    "head": "fdbfe1358a499c42e20350686b5f7371624e5977",
    "short_head": "fdbfe13",
    "branch": "main",
    "tracked_dirty": true,
    "tracked_status": [
      "M hub/plan_terapeutico.py"
    ]
  },
  "command": [
    "qa\\capture_v8.py",
    "--app",
    "hub",
    "--view",
    "detalle",
    "--theme",
    "light",
    "--out",
    "qa/_captures_v8/iter33_bienestar_after"
  ],
  "cwd": "C:\\Users\\nosom\\Desktop\\nm_suite",
  "isolation_scope": "subprocess_per_recipe",
  "auto_residual_popup_capture": false,
  "success": 1,
  "failed": 0,
  "total": 1,
  "expected_recipe_captures": 1,
  "elapsed_seconds": 4.8,
  "themes": [
    "light"
  ],
  "resolutions": [
    "960x600"
  ],
  "requested_scale_factor": 1.0,
  "output_dir": "qa\\_captures_v8\\iter33_bienestar_after",
  "matrix_paths": {
    "csv": "qa\\_captures_v8\\iter33_bienestar_after\\CAPTURE_MATRIX.csv",
    "markdown": "qa\\_captures_v8\\iter33_bienestar_after\\CAPTURE_MATRIX.md"
  },
  "evidence_summary": {
    "semantic_visual_review": "NOT_RUN",
    "visual_review_outcome": "REVIEW_INCOMPLETE",
    "technical_capture_only": true,
    "state_valid_capture_count": 1,
    "technical_valid_capture_count": 1,
    "technical_960_capture_count": 1,
    "main_base_capture_count": 1,
    "main_scale125_capture_count": 0,
    "natural_dialog_capture_count": 0,
    "main_scaled_other_capture_count": 0,
    "unsupported_contract_count": 0,
    "invalid_or_unsupported_contract_count": 0,
    "contract_mismatch_count": 0,
    "unique_hash_count": 1,
    "duplicate_group_count": 0,
    "duplicate_groups": [],
    "status_counts": {
      "CAPTURED_VALID": 1
    },
    "requires_runtime": [],
    "requires_data_state": [],
    "wrong_view_or_fallback": [],
    "main_capture_contract_mismatch": [],
    "blank_or_flat": []
  },
  "results": [
    {
      "file": "hub-detalle-light-960x600.png",
      "app": "hub",
      "view": "detalle",
      "theme": "light",
      "resolution": "960x600",
      "requested_resolution": "960x600",
      "requested_logical_resolution": "960x600",
      "captured_logical_resolution": "960x600",
      "captured_pixel_resolution": "960x600",
      "device_pixel_ratio": 1.0,
      "requested_scale_factor": 1.0,
      "evidence_contract": "main_base",
      "success": true,
      "size_bytes": 50240,
      "is_dialog_or_auxiliary": false,
      "is_child_dialog": false,
      "actual_resolution": "960x600",
      "isolation_scope": "subprocess_per_recipe",
      "evidence_flags": [],
      "evidence_notes": [],
      "technical_capture_valid": true,
      "state_evidence_valid": true,
      "content_metrics": {
        "gray_mean": 0.9012,
        "gray_stddev": 0.1389
      },
      "sha256": "b76a62efa0674c812c1a54ac3f9dfaee66017b8946cd165b8e4884c3d478e082",
      "capture_status": "CAPTURED_VALID"
    }
  ]
}