{
  "surface_key": "suite:registro-success@light",
  "status": "FAIL",
  "repair_decision": "FIX_PRODUCT_STRONG",
  "passed": false,
  "failures": [
    "ssim<0.92"
  ],
  "metrics": {
    "target_size": {
      "w": 960,
      "h": 600
    },
    "actual_size": {
      "w": 960,
      "h": 600
    },
    "size_mismatch": false,
    "ssim": 0.35484,
    "mean_abs_diff": 0.01922,
    "max_abs_diff": 0.80784,
    "changed_pixel_floor": 12,
    "changed_pixels": 35361,
    "total_pixels": 576000,
    "changed_pixel_ratio": 0.06139
  },
  "regions": [
    {
      "x": 0,
      "y": 43,
      "w": 960,
      "h": 557,
      "area": 9102,
      "area_ratio": 0.015802,
      "hint": "layout_shift_or_spacing"
    },
    {
      "x": 431,
      "y": 245,
      "w": 132,
      "h": 89,
      "area": 6825,
      "area_ratio": 0.011849,
      "hint": "component_region"
    },
    {
      "x": 450,
      "y": 198,
      "w": 60,
      "h": 47,
      "area": 2153,
      "area_ratio": 0.003738,
      "hint": "component_region"
    },
    {
      "x": 220,
      "y": 82,
      "w": 520,
      "h": 18,
      "area": 1518,
      "area_ratio": 0.002635,
      "hint": "component_region"
    },
    {
      "x": 81,
      "y": 16,
      "w": 168,
      "h": 17,
      "area": 1454,
      "area_ratio": 0.002524,
      "hint": "component_region"
    },
    {
      "x": 490,
      "y": 383,
      "w": 441,
      "h": 14,
      "area": 980,
      "area_ratio": 0.001701,
      "hint": "component_region"
    },
    {
      "x": 32,
      "y": 480,
      "w": 896,
      "h": 1,
      "area": 896,
      "area_ratio": 0.001556,
      "hint": "layout_shift_or_spacing"
    },
    {
      "x": 34,
      "y": 157,
      "w": 892,
      "h": 1,
      "area": 892,
      "area_ratio": 0.001549,
      "hint": "layout_shift_or_spacing"
    }
  ],
  "canonical": {
    "surface_key": "suite:registro-success@light",
    "app": "suite",
    "view": "registro-success",
    "theme": "light",
    "resolution": "960x600",
    "file": "suite-registro-success-light-960x600.png",
    "path": "C:\\Users\\nosom\\Desktop\\nm_suite\\qa\\_mockup_canonical\\suite-registro-success-light-960x600.png",
    "screen": "registro",
    "state": "ok",
    "surface": "window",
    "capture_selector": ".window",
    "dom_w": 960,
    "dom_h": 600,
    "dom_size_match": true,
    "mockup_sha256": "0fa4b834e50a8936e829a493b6b31c9e181edb84621f9f7861f98ea609a07c87"
  },
  "actual_path": "qa\\_captures_compare_20260628\\suite-registro-success-light-960x600.png",
  "diff_path": "reports\\e2e\\visual_parity_compare_20260628\\suite_registro-success_light\\suite-registro-success-light-960x600-diff.png",
  "report_path": "reports\\e2e\\visual_parity_compare_20260628\\suite_registro-success_light\\result.json",
  "agent_package": {
    "surface_key": "suite:registro-success@light",
    "status": "FAIL",
    "repair_decision": "FIX_PRODUCT_STRONG",
    "passed": false,
    "failures": [
      "ssim<0.92"
    ],
    "metrics": {
      "target_size": {
        "w": 960,
        "h": 600
      },
      "actual_size": {
        "w": 960,
        "h": 600
      },
      "size_mismatch": false,
      "ssim": 0.35484,
      "mean_abs_diff": 0.01922,
      "max_abs_diff": 0.80784,
      "changed_pixel_floor": 12,
      "changed_pixels": 35361,
      "total_pixels": 576000,
      "changed_pixel_ratio": 0.06139
    },
    "thresholds": {
      "min_ssim": 0.92,
      "max_mean_abs_diff": 0.035,
      "max_changed_pixel_ratio": 0.08,
      "changed_pixel_floor": 12,
      "render_noise_max_mean_abs_diff": 0.004,
      "render_noise_max_changed_pixel_ratio": 0.003,
      "render_noise_max_region_area_ratio": 0.001,
      "strong_fail_changed_pixel_ratio": 0.18,
      "strong_fail_region_area_ratio": 0.08,
      "strong_fail_mean_abs_diff": 0.08,
      "max_regions": 8
    },
    "canonical_index": {
      "root": "C:\\Users\\nosom\\Desktop\\nm_suite\\qa\\_mockup_canonical",
      "total_surfaces": 86,
      "mockup_sha256": "0fa4b834e50a8936e829a493b6b31c9e181edb84621f9f7861f98ea609a07c87",
      "all_captured": true,
      "all_sizes_match": true,
      "all_dom_sizes_match": true
    },
    "canonical": {
      "surface_key": "suite:registro-success@light",
      "app": "suite",
      "view": "registro-success",
      "theme": "light",
      "resolution": "960x600",
      "file": "suite-registro-success-light-960x600.png",
      "path": "C:\\Users\\nosom\\Desktop\\nm_suite\\qa\\_mockup_canonical\\suite-registro-success-light-960x600.png",
      "screen": "registro",
      "state": "ok",
      "surface": "window",
      "capture_selector": ".window",
      "dom_w": 960,
      "dom_h": 600,
      "dom_size_match": true,
      "mockup_sha256": "0fa4b834e50a8936e829a493b6b31c9e181edb84621f9f7861f98ea609a07c87"
    },
    "actual_path": "qa\\_captures_compare_20260628\\suite-registro-success-light-960x600.png",
    "diff_path": "reports\\e2e\\visual_parity_compare_20260628\\suite_registro-success_light\\suite-registro-success-light-960x600-diff.png",
    "largest_regions": [
      {
        "x": 0,
        "y": 43,
        "w": 960,
        "h": 557,
        "area": 9102,
        "area_ratio": 0.015802,
        "hint": "layout_shift_or_spacing"
      },
      {
        "x": 431,
        "y": 245,
        "w": 132,
        "h": 89,
        "area": 6825,
        "area_ratio": 0.011849,
        "hint": "component_region"
      },
      {
        "x": 450,
        "y": 198,
        "w": 60,
        "h": 47,
        "area": 2153,
        "area_ratio": 0.003738,
        "hint": "component_region"
      },
      {
        "x": 220,
        "y": 82,
        "w": 520,
        "h": 18,
        "area": 1518,
        "area_ratio": 0.002635,
        "hint": "component_region"
      },
      {
        "x": 81,
        "y": 16,
        "w": 168,
        "h": 17,
        "area": 1454,
        "area_ratio": 0.002524,
        "hint": "component_region"
      },
      {
        "x": 490,
        "y": 383,
        "w": 441,
        "h": 14,
        "area": 980,
        "area_ratio": 0.001701,
        "hint": "component_region"
      },
      {
        "x": 32,
        "y": 480,
        "w": 896,
        "h": 1,
        "area": 896,
        "area_ratio": 0.001556,
        "hint": "layout_shift_or_spacing"
      },
      {
        "x": 34,
        "y": 157,
        "w": 892,
        "h": 1,
        "area": 892,
        "area_ratio": 0.001549,
        "hint": "layout_shift_or_spacing"
      }
    ],
    "what_to_check_first": [
      "Inspect the largest diff regions first; this usually means layout, modal position, missing widget, or wrong state.",
      "Compare Qt widget geometry against the canonical manifest resolution and selector."
    ],
    "do_not_touch_if": [
      "The canonical manifest has all_dom_sizes_match=false or the capture selector is stale.",
      "The actual screenshot contains an unrelated dialog, hover state, focus ring, cursor, toast, or loading state."
    ],
    "repair_hints": [
      "Open the largest bbox first: {'x': 0, 'y': 43, 'w': 960, 'h': 557, 'area': 9102, 'area_ratio': 0.015802, 'hint': 'layout_shift_or_spacing'}.",
      "After a product patch, rerun only this surface before expanding to the full visual suite."
    ]
  }
}